steeleagle_sdk/api/__init__.py
steeleagle_sdk/api/base.py
steeleagle_sdk/api/compute.py
steeleagle_sdk/api/native.py
steeleagle_sdk/api/actions/__init__.py
steeleagle_sdk/api/actions/native.py
steeleagle_sdk/api/actions/primitives/README.md
steeleagle_sdk/api/actions/primitives/__init__.py
steeleagle_sdk/api/actions/primitives/compute.py
steeleagle_sdk/api/actions/primitives/control.py
steeleagle_sdk/api/actions/primitives/report.py
steeleagle_sdk/api/actions/procedures/__init__.py
steeleagle_sdk/api/actions/procedures/procedures.py
steeleagle_sdk/api/actions/tactics/__init__.py
steeleagle_sdk/api/actions/tactics/tactics.py
steeleagle_sdk/api/datatypes/README.md
steeleagle_sdk/api/datatypes/__init__.py
steeleagle_sdk/api/datatypes/common.py
steeleagle_sdk/api/datatypes/compute.py
steeleagle_sdk/api/datatypes/control.py
steeleagle_sdk/api/datatypes/report.py
steeleagle_sdk/api/datatypes/result.py
steeleagle_sdk/api/datatypes/telemetry.py
steeleagle_sdk/api/datatypes/waypoint.py
steeleagle_sdk/api/events/__init__.py
steeleagle_sdk/api/events/compositions.py
steeleagle_sdk/api/events/singulars.py
steeleagle_sdk/dsl/__init__.py
steeleagle_sdk/dsl/compiler/__init__.py
steeleagle_sdk/dsl/compiler/ir.py
steeleagle_sdk/dsl/compiler/loader.py
steeleagle_sdk/dsl/compiler/registry.py
steeleagle_sdk/dsl/compiler/resolver.py
steeleagle_sdk/dsl/compiler/transformer.py
steeleagle_sdk/dsl/compiler/validator.py
steeleagle_sdk/dsl/grammar/dronedsl.lark
steeleagle_sdk/dsl/runtime/fsm.py
steeleagle_sdk/protocol/README.md
steeleagle_sdk/protocol/__init__.py
steeleagle_sdk/protocol/common_pb2.py
steeleagle_sdk/protocol/descriptors.py
steeleagle_sdk/protocol/protocol.desc
steeleagle_sdk/protocol/rpc_helpers.py
steeleagle_sdk/protocol/messages/__init__.py
steeleagle_sdk/protocol/messages/result_pb2.py
steeleagle_sdk/protocol/messages/telemetry_pb2.py
steeleagle_sdk/protocol/services/__init__.py
steeleagle_sdk/protocol/services/compute_service_pb2.py
steeleagle_sdk-1.0.13.dist-info/METADATA
steeleagle_sdk-1.0.13.dist-info/WHEEL
steeleagle_sdk-1.0.13.dist-info/entry_points.txt
steeleagle_sdk-1.0.13.dist-info/licenses/LICENSE
steeleagle_sdk-1.0.13.dist-info/RECORD
