Metadata-Version: 2.4
Name: steeleagle_sdk
Version: 1.0.13
Summary: SDK for interacting with SteelEagle vehicles.
Project-URL: Homepage, https://cmusatyalab.github.io/steeleagle/
Project-URL: Documentation, https://cmusatyalab.github.io/steeleagle/
Project-URL: Repository, https://github.com/cmusatyalab/steeleagle
Project-URL: Issues, https://github.com/cmusatyalab/steeleagle/issues
Project-URL: Changelog, https://github.com/cmusatyalab/steeleagle/releases
Author-email: Mihir Bala <mbala@andrew.cmu.edu>, Thomas Eiszler <teiszler@andrew.cmu.edu>, Anthony Chen <xianglic@andrew.cmu.edu>, Aditya Chanana <achanana@andrew.cmu.edu>
Maintainer-email: Thomas Eiszler <teiszler@andrew.cmu.edu>
License:                     GNU GENERAL PUBLIC LICENSE
License-File: LICENSE
Keywords: autonomous,drone,edge,robots,uas,uav,ugv,vision
Classifier: Development Status :: 3 - Alpha
Classifier: Operating System :: OS Independent
Classifier: Programming Language :: Python :: 3
Requires-Python: >=3.11
Requires-Dist: folium>=0.20.0
Requires-Dist: grpcio>=1.74.0
Requires-Dist: lark>=1.2.2
Requires-Dist: matplotlib>=3.10.6
Requires-Dist: protobuf>=3.12
Requires-Dist: pydantic>=2.11.7
Requires-Dist: pygls
Requires-Dist: shapely>=2.1.1
